{
  "people": [
    {
      "_id": "61f7a5b5de680730082757e4",
      "index": 0,
      "guid": "7f19e2ce-2e1c-473d-aa97-00ede823ce1d",
      "isActive": false,
      "balance": "$3,711.26",
      "picture": "http://placehold.it/32x32",
      "age": 38,
      "eyeColor": "blue",
      "name": "Sheri Hester",
      "gender": "female",
      "company": "COMVOY",
      "email": "sherihester@comvoy.com",
      "phone": "+1 (807) 474-3675",
      "address": "311 Fleet Walk, Virgie, Indiana, 1686",
      "about": "Ipsum exercitation esse excepteur dolore voluptate dolor pariatur ut. Magna culpa sit do nisi sint fugiat ea deserunt esse anim tempor. Laborum Lorem aliqua duis irure culpa fugiat in duis. Enim nulla labore pariatur consectetur ea qui sit commodo. Minim magna ipsum eiusmod duis est amet ipsum. Fugiat ullamco tempor elit aliqua. Dolore commodo minim officia dolor minim est dolor dolor.\r\n",
      "registered": "2015-03-06T08:05:23 -06:-30",
      "latitude": 87.628389,
      "longitude": 125.556994,
      "tags": [
        "irure",
        "magna",
        "excepteur",
        "laborum",
        "labore",
        "anim",
        "reprehenderit"
      ],
      "friends": [
        {
          "id": 0,
          "name": "Gertrude Hawkins"
        },
        {
          "id": 1,
          "name": "Tate Kaufman"
        },
        {
          "id": 2,
          "name": "Marla Villarreal"
        }
      ],
      "greeting": "Hello, Sheri Hester! You have 6 unread messages.",
      "favoriteFruit": "apple"
    },
    {
      "_id": "61f7a5b520275585138d451a",
      "index": 1,
      "guid": "2aff87c3-ec04-493e-afcf-67b76bb6a62a",
      "isActive": true,
      "balance": "$1,081.22",
      "picture": "http://placehold.it/32x32",
      "age": 38,
      "eyeColor": "brown",
      "name": "Frost Pennington",
      "gender": "male",
      "company": "TELEQUIET",
      "email": "frostpennington@telequiet.com",
      "phone": "+1 (971) 534-3189",
      "address": "183 Grand Street, Brecon, New Mexico, 958",
      "about": "Sunt consectetur ut ad dolore sint sit ad labore nulla excepteur. Consectetur ad amet qui cillum cillum ullamco laboris minim. Aute et pariatur adipisicing Lorem nostrud ut ea cupidatat irure tempor ipsum sunt. Nostrud duis culpa non velit enim culpa excepteur exercitation est ipsum nisi id. Id qui id nulla dolore cillum elit culpa mollit duis incididunt occaecat. Incididunt cupidatat ex nostrud tempor.\r\n",
      "registered": "2020-10-28T05:27:26 -06:-30",
      "latitude": 79.144945,
      "longitude": 107.872734,
      "tags": [
        "aliquip",
        "sit",
        "non",
        "proident",
        "occaecat",
        "eiusmod",
        "est"
      ],
      "friends": [
        {
          "id": 0,
          "name": "Riggs Norman"
        },
        {
          "id": 1,
          "name": "Mia Ward"
        },
        {
          "id": 2,
          "name": "Paul Baldwin"
        }
      ],
      "greeting": "Hello, Frost Pennington! You have 4 unread messages.",
      "favoriteFruit": "apple"
    },
    {
      "_id": "61f7a5b5bdde68f668cdc37c",
      "index": 2,
      "guid": "d25ae5eb-b2da-49a9-936e-421ad615df13",
      "isActive": false,
      "balance": "$3,318.51",
      "picture": "http://placehold.it/32x32",
      "age": 34,
      "eyeColor": "blue",
      "name": "Annabelle Whitaker",
      "gender": "female",
      "company": "EPLODE",
      "email": "annabellewhitaker@eplode.com",
      "phone": "+1 (821) 568-2461",
      "address": "452 Bragg Street, Greer, Texas, 5972",
      "about": "Amet ex mollit laboris irure irure consectetur et deserunt magna nulla exercitation. Anim anim pariatur velit ipsum Lorem. Enim nulla enim dolor reprehenderit occaecat tempor id cillum aliquip laboris. Ex ut occaecat pariatur occaecat mollit dolor consectetur nisi enim sint. Adipisicing magna nostrud sint in nostrud ex nulla mollit.\r\n",
      "registered": "2018-06-06T08:51:07 -06:-30",
      "latitude": 15.454281,
      "longitude": -125.439096,
      "tags": [
        "adipisicing",
        "magna",
        "exercitation",
        "irure",
        "nostrud",
        "ut",
        "qui"
      ],
      "friends": [
        {
          "id": 0,
          "name": "Bates Daniel"
        },
        {
          "id": 1,
          "name": "Wilda Carson"
        },
        {
          "id": 2,
          "name": "Sims Burch"
        }
      ],
      "greeting": "Hello, Annabelle Whitaker! You have 8 unread messages.",
      "favoriteFruit": "apple"
    },
    {
      "_id": "61f7a5b52d9e3328696ebd7e",
      "index": 3,
      "guid": "f2717956-3339-499e-a4b8-ccc77271a097",
      "isActive": false,
      "balance": "$3,244.07",
      "picture": "http://placehold.it/32x32",
      "age": 37,
      "eyeColor": "blue",
      "name": "Lyons Conley",
      "gender": "male",
      "company": "FURNIGEER",
      "email": "lyonsconley@furnigeer.com",
      "phone": "+1 (847) 505-3464",
      "address": "121 Duryea Court, Wyano, Guam, 4793",
      "about": "Eu ipsum exercitation culpa aliquip excepteur. Deserunt anim ipsum consectetur duis mollit dolor ad. Tempor incididunt sit ipsum exercitation proident duis ipsum laborum sunt. Tempor nisi consequat mollit ex irure duis consectetur dolore ipsum ipsum dolor cillum cupidatat eiusmod.\r\n",
      "registered": "2015-08-31T02:14:50 -06:-30",
      "latitude": -27.904048,
      "longitude": 46.454993,
      "tags": [
        "sit",
        "occaecat",
        "fugiat",
        "Lorem",
        "aliquip",
        "ad",
        "eiusmod"
      ],
      "friends": [
        {
          "id": 0,
          "name": "Walter Cruz"
        },
        {
          "id": 1,
          "name": "Josephine Cline"
        },
        {
          "id": 2,
          "name": "Roy Whitney"
        }
      ],
      "greeting": "Hello, Lyons Conley! You have 8 unread messages.",
      "favoriteFruit": "banana"
    },
    {
      "_id": "61f7a5b5c5fab51215631692",
      "index": 4,
      "guid": "c593073b-59b2-44f9-84e4-c3cb476e422f",
      "isActive": false,
      "balance": "$3,190.63",
      "picture": "http://placehold.it/32x32",
      "age": 26,
      "eyeColor": "brown",
      "name": "Celina Weaver",
      "gender": "female",
      "company": "GYNKO",
      "email": "celinaweaver@gynko.com",
      "phone": "+1 (916) 489-3499",
      "address": "700 Barlow Drive, Brownlee, Idaho, 4109",
      "about": "Tempor tempor non nulla commodo est ut. Consequat in et eu anim sint amet veniam ex eu adipisicing sint labore proident. Duis minim cillum duis id sint irure sunt elit aliqua officia sint. Nostrud culpa in est magna tempor dolor voluptate occaecat proident Lorem ut officia voluptate aute. Nulla laboris enim ex ea aliqua sint consectetur.\r\n",
      "registered": "2014-07-18T06:45:08 -06:-30",
      "latitude": -56.475605,
      "longitude": 151.928122,
      "tags": [
        "mollit",
        "ullamco",
        "veniam",
        "labore",
        "et",
        "minim",
        "excepteur"
      ],
      "friends": [
        {
          "id": 0,
          "name": "Bass Rush"
        },
        {
          "id": 1,
          "name": "Cora Baird"
        },
        {
          "id": 2,
          "name": "Sanchez Blanchard"
        }
      ],
      "greeting": "Hello, Celina Weaver! You have 7 unread messages.",
      "favoriteFruit": "banana"
    },
    {
      "_id": "61f7a5b5a7ff1983ec94a966",
      "index": 5,
      "guid": "67499502-4ff7-439f-a548-ef7692df40fd",
      "isActive": true,
      "balance": "$1,769.32",
      "picture": "http://placehold.it/32x32",
      "age": 24,
      "eyeColor": "blue",
      "name": "Juarez Dyer",
      "gender": "male",
      "company": "BULLZONE",
      "email": "juarezdyer@bullzone.com",
      "phone": "+1 (973) 582-3530",
      "address": "649 Metrotech Courtr, Orovada, District Of Columbia, 2305",
      "about": "Minim ex enim tempor non aute adipisicing. Tempor occaecat qui proident Lorem id velit dolore velit ex. Laboris officia ad ut laborum qui adipisicing consequat reprehenderit irure aute.\r\n",
      "registered": "2020-01-23T06:46:03 -06:-30",
      "latitude": -1.37602,
      "longitude": 104.232704,
      "tags": ["sunt", "et", "aliquip", "tempor", "nisi", "est", "nulla"],
      "friends": [
        {
          "id": 0,
          "name": "Brewer Cross"
        },
        {
          "id": 1,
          "name": "Rebekah Walter"
        },
        {
          "id": 2,
          "name": "Julie Mcgee"
        }
      ],
      "greeting": "Hello, Juarez Dyer! You have 2 unread messages.",
      "favoriteFruit": "apple"
    }
  ]
}
